{
    "CallerReference": "a532d5df-eedb-4027-b88f-c985a65c69cd",
    "Aliases": {
        "Quantity": 2,
        "Items": [
            "www.masky.net",
            "masky.net"
        ]
    },
    "DefaultRootObject": "index.html",
    "Origins": {
        "Quantity": 2,
        "Items": [
            {
                "Id": "api-gateway-origin",
                "DomainName": "b4feblbni7.execute-api.us-east-1.amazonaws.com",
                "OriginPath": "/production",
                "CustomHeaders": {
                    "Quantity": 0
                },
                "CustomOriginConfig": {
                    "HTTPPort": 80,
                    "HTTPSPort": 443,
                    "OriginProtocolPolicy": "https-only",
                    "OriginSslProtocols": {
                        "Quantity": 1,
                        "Items": [
                            "TLSv1.2"
                        ]
                    },
                    "OriginReadTimeout": 30,
                    "OriginKeepaliveTimeout": 5
                },
                "ConnectionAttempts": 3,
                "ConnectionTimeout": 10,
                "OriginShield": {
                    "Enabled": false
                },
                "OriginAccessControlId": ""
            },
            {
                "Id": "masky.net.s3.us-east-1.amazonaws.com-mgulezuaft7",
                "DomainName": "masky.net.s3.us-east-1.amazonaws.com",
                "OriginPath": "",
                "CustomHeaders": {
                    "Quantity": 0
                },
                "S3OriginConfig": {
                    "OriginAccessIdentity": ""
                },
                "ConnectionAttempts": 3,
                "ConnectionTimeout": 10,
                "OriginShield": {
                    "Enabled": false
                },
                "OriginAccessControlId": "E21V25C59D5TQA"
            }
        ]
    },
    "OriginGroups": {
        "Quantity": 0
    },
    "DefaultCacheBehavior": {
        "TargetOriginId": "masky.net.s3.us-east-1.amazonaws.com-mgulezuaft7",
        "TrustedSigners": {
            "Enabled": false,
            "Quantity": 0
        },
        "TrustedKeyGroups": {
            "Enabled": false,
            "Quantity": 0
        },
        "ViewerProtocolPolicy": "redirect-to-https",
        "AllowedMethods": {
            "Quantity": 2,
            "Items": [
                "HEAD",
                "GET"
            ],
            "CachedMethods": {
                "Quantity": 2,
                "Items": [
                    "HEAD",
                    "GET"
                ]
            }
        },
        "SmoothStreaming": false,
        "Compress": true,
        "LambdaFunctionAssociations": {
            "Quantity": 0
        },
        "FunctionAssociations": {
            "Quantity": 1,
            "Items": [
                {
                    "FunctionARN": "arn:aws:cloudfront::218827615080:function/www-redirect-masky",
                    "EventType": "viewer-request"
                }
            ]
        },
        "FieldLevelEncryptionId": "",
        "CachePolicyId": "658327ea-f89d-4fab-a63d-7e88639e58f6"
    },
    "CacheBehaviors": {
        "Quantity": 1,
        "Items": [
            {
                "PathPattern": "/api/*",
                "TargetOriginId": "api-gateway-origin",
                "TrustedSigners": {
                    "Enabled": false,
                    "Quantity": 0
                },
                "TrustedKeyGroups": {
                    "Enabled": false,
                    "Quantity": 0
                },
                "ViewerProtocolPolicy": "https-only",
                "AllowedMethods": {
                    "Quantity": 7,
                    "Items": [
                        "HEAD",
                        "DELETE",
                        "POST",
                        "GET",
                        "OPTIONS",
                        "PUT",
                        "PATCH"
                    ],
                    "CachedMethods": {
                        "Quantity": 3,
                        "Items": [
                            "HEAD",
                            "GET",
                            "OPTIONS"
                        ]
                    }
                },
                "SmoothStreaming": false,
                "Compress": true,
                "LambdaFunctionAssociations": {
                    "Quantity": 0
                },
                "FunctionAssociations": {
                    "Quantity": 0
                },
                "FieldLevelEncryptionId": "",
                "CachePolicyId": "4135ea2d-6df8-44a3-9df3-4b5a84be39ad",
                "OriginRequestPolicyId": "216adef6-5c7f-47e4-b989-5492eafa07d3",
                "ResponseHeadersPolicyId": "60669652-455b-4ae9-85a4-c4c02393f86c"
            }
        ]
    },
    "CustomErrorResponses": {
        "Quantity": 0
    },
    "Comment": "",
    "Logging": {
        "Enabled": false,
        "IncludeCookies": false,
        "Bucket": "",
        "Prefix": ""
    },
    "PriceClass": "PriceClass_All",
    "Enabled": true,
    "ViewerCertificate": {
        "CloudFrontDefaultCertificate": false,
        "ACMCertificateArn": "arn:aws:acm:us-east-1:218827615080:certificate/299bc5b3-6563-491e-88b4-f6ad7d66b053",
        "SSLSupportMethod": "sni-only",
        "MinimumProtocolVersion": "TLSv1.2_2021",
        "Certificate": "arn:aws:acm:us-east-1:218827615080:certificate/299bc5b3-6563-491e-88b4-f6ad7d66b053",
        "CertificateSource": "acm"
    },
    "Restrictions": {
        "GeoRestriction": {
            "RestrictionType": "none",
            "Quantity": 0
        }
    },
    "WebACLId": "",
    "HttpVersion": "http2",
    "IsIPV6Enabled": true,
    "ContinuousDeploymentPolicyId": "",
    "Staging": false
}